leveropen/__init__.py
leveropen/api_errors.py
leveropen/client.py
leveropen/dataset.py
leveropen/l_series.py
leveropen/lever.py
leveropen/protocol.py
leveropen/utils.py
leveropen-0.0.2.dist-info/LICENSE
leveropen-0.0.2.dist-info/METADATA
leveropen-0.0.2.dist-info/WHEEL
leveropen-0.0.2.dist-info/top_level.txt
leveropen-0.0.2.dist-info/RECORD
