Metadata-Version: 2.1
Name: leveropen
Version: 0.0.2
Summary: Python wrapper for Lever Open API
Home-page: https://leveropen.readthedocs.io/en/latest/
License: MIT
Download-URL: https://github.com/n-n-s/leveropen
Platform: UNKNOWN
Classifier: Development Status :: 3 - Alpha
Classifier: License :: OSI Approved :: MIT License
Classifier: Programming Language :: Python :: 3
Classifier: Programming Language :: Python :: 3.9
Requires-Dist: requests (==2.25.1)
Requires-Dist: pandas (==1.2.4)
Requires-Dist: tqdm (==4.60.0)
Requires-Dist: halo (==0.0.31)
Requires-Dist: coveralls (==3.1.0)
Requires-Dist: sphinx-rtd-theme (==0.5.2)
